examples/__init__.py
examples/bigiq_revoke_license.py
examples/cs_beacon.py
examples/cs_subscription.py
examples/extension_as3.py
f5sdk/__init__.py
f5sdk/base_clients.py
f5sdk/constants.py
f5sdk/decorators.py
f5sdk/exceptions.py
f5sdk/logger.py
f5sdk/bigip/__init__.py
f5sdk/bigip/mgmt_client.py
f5sdk/bigip/dns/__init__.py
f5sdk/bigip/dns/datacenters.py
f5sdk/bigip/dns/pools.py
f5sdk/bigip/dns/servers.py
f5sdk/bigip/extension/__init__.py
f5sdk/bigip/extension/extension_as3.py
f5sdk/bigip/extension/extension_cf.py
f5sdk/bigip/extension/extension_do.py
f5sdk/bigip/extension/extension_metadata.json
f5sdk/bigip/extension/extension_metadata.py
f5sdk/bigip/extension/extension_ts.py
f5sdk/bigip/extension/package/__init__.py
f5sdk/bigip/extension/package/operation.py
f5sdk/bigip/extension/service/__init__.py
f5sdk/bigip/extension/service/operation.py
f5sdk/bigiq/__init__.py
f5sdk/bigiq/mgmt_client.py
f5sdk/bigiq/licensing/__init__.py
f5sdk/bigiq/licensing/assignments.py
f5sdk/bigiq/licensing/pools/__init__.py
f5sdk/bigiq/licensing/pools/member_management.py
f5sdk/bigiq/licensing/pools/reg_key.py
f5sdk/bigiq/licensing/pools/utility.py
f5sdk/cs/__init__.py
f5sdk/cs/mgmt_client.py
f5sdk/cs/accounts/__init__.py
f5sdk/cs/accounts/account.py
f5sdk/cs/beacon/__init__.py
f5sdk/cs/beacon/declare/__init__.py
f5sdk/cs/beacon/declare/declare.py
f5sdk/cs/beacon/insights/__init__.py
f5sdk/cs/beacon/insights/insights.py
f5sdk/cs/beacon/token/__init__.py
f5sdk/cs/beacon/token/token.py
f5sdk/cs/subscriptions/__init__.py
f5sdk/cs/subscriptions/subscription.py
f5sdk/scripts/__init__.py
f5sdk/scripts/extension/__init__.py
f5sdk/scripts/extension/extension_info.json
f5sdk/scripts/extension/generate_metadata.py
f5sdk/utils/__init__.py
f5sdk/utils/file_utils.py
f5sdk/utils/http_utils.py
f5sdk/utils/misc_utils.py
f5_sdk_python-0.9.2.dist-info/LICENSE
f5_sdk_python-0.9.2.dist-info/METADATA
f5_sdk_python-0.9.2.dist-info/WHEEL
f5_sdk_python-0.9.2.dist-info/top_level.txt
f5_sdk_python-0.9.2.dist-info/RECORD
