Metadata-Version: 2.1
Name: f5-sdk-python
Version: 0.9.2
Summary: F5 SDK
Home-page: UNKNOWN
Author: F5 Ecosystems Group
Author-email: solutionsfeedback@f5.com
License: Apache License 2.0
Platform: UNKNOWN
